Metadata-Version: 1.0
Name: distributionsRhomzi
Version: 0.2
Summary: Gaussian & Binomial distributions
Home-page: UNKNOWN
Author: Eromonsele O
Author-email: UNKNOWN
License: UNKNOWN
Platform: UNKNOWN
